{
    "type": "produce_solution",
    "id": "129c89f584cc44ea84c2891be408c0d8",
    "name": "fes千奈",
    "description": "干劲",
    "data": {
        "mode": "master",
        "idol": "i_card-skin-kcna-3-007",
        "memory_set": 2,
        "support_card_set": null,
        "auto_set_memory": false,
        "auto_set_support_card": true,
        "use_pt_boost": false,
        "use_note_boost": false,
        "follow_producer": true,
        "self_study_lesson": "dance",
        "prefer_lesson_ap": true,
        "actions_order": [
            "recommended",
            "dance",
            "visual",
            "vocal",
            "study",
            "outing",
            "rest",
            "allowance",
            "consult"
        ],
        "recommend_card_detection_mode": "normal",
        "use_ap_drink": true,
        "skip_commu": true
    }
}