{
    "type": "produce_solution",
    "id": "a5a880ed230142cc85e83f142af21dbf",
    "name": "【Campus mode!!】千奈（逻辑）",
    "description": "pro",
    "data": {
        "mode": "pro",
        "idol": "i_card-skin-kcna-3-007",
        "memory_set": null,
        "support_card_set": null,
        "auto_set_memory": true,
        "auto_set_support_card": true,
        "use_pt_boost": false,
        "use_note_boost": false,
        "follow_producer": true,
        "self_study_lesson": "dance",
        "prefer_lesson_ap": false,
        "actions_order": [
            "recommended",
            "dance",
            "visual",
            "vocal",
            "study",
            "allowance",
            "outing",
            "consult",
            "rest"
        ],
        "recommend_card_detection_mode": "normal",
        "use_ap_drink": true,
        "skip_commu": true
    }
}